udemy_enroller/__init__.py
udemy_enroller/cli.py
udemy_enroller/driver_manager.py
udemy_enroller/exceptions.py
udemy_enroller/http_utils.py
udemy_enroller/logger.py
udemy_enroller/runner.py
udemy_enroller/scrapers/__init__.py
udemy_enroller/scrapers/base_scraper.py
udemy_enroller/scrapers/coursevania.py
udemy_enroller/scrapers/discudemy.py
udemy_enroller/scrapers/freebiesglobal.py
udemy_enroller/scrapers/idownloadcoupon.py
udemy_enroller/scrapers/manager.py
udemy_enroller/scrapers/tutorialbar.py
udemy_enroller/settings.py
udemy_enroller/udemy_rest.py
udemy_enroller/udemy_ui.py
udemy_enroller/utils.py
udemy_enroller-4.1.4.dist-info/entry_points.txt
udemy_enroller-4.1.4.dist-info/METADATA
udemy_enroller-4.1.4.dist-info/WHEEL
udemy_enroller-4.1.4.dist-info/LICENSE
udemy_enroller-4.1.4.dist-info/RECORD
