Metadata-Version: 2.1
Name: udemy-enroller
Version: 4.1.4
Summary: 
Home-page: https://github.com/aapatre/Automatic-Udemy-Course-Enroller-GET-PAID-UDEMY-COURSES-for-FREE
Keywords: udemy,education,enroll
Author: aapatre
Author-email: udemyenroller@gmail.com
Requires-Python: >=3.8,<4.0
Classifier: Development Status :: 4 - Beta
Classifier: Intended Audience :: Education
Classifier: License :: OSI Approved :: GNU Lesser General Public License v3 (LGPLv3)
Classifier: Programming Language :: Python :: 3
Classifier: Programming Language :: Python :: 3.8
Classifier: Programming Language :: Python :: 3.9
Classifier: Programming Language :: Python :: 3.10
Classifier: Programming Language :: Python :: 3.11
Classifier: Programming Language :: Python :: 3.8
Requires-Dist: aiohttp[speedups] (==3.8.4)
Requires-Dist: beautifulsoup4 (==4.11.1)
Requires-Dist: cloudscraper (==1.2.71)
Requires-Dist: price-parser (==0.3.4)
Requires-Dist: requests (==2.31.0)
Requires-Dist: ruamel.yaml (==0.17.32)
Requires-Dist: selenium (==4.10.0)
Requires-Dist: webdriver-manager (==3.8.6)
